mcsmapi/__init__.py
mcsmapi/exceptions.py
mcsmapi/pool.py
mcsmapi/request.py
mcsmapi/apis/__init__.py
mcsmapi/apis/daemon.py
mcsmapi/apis/file.py
mcsmapi/apis/image.py
mcsmapi/apis/instance.py
mcsmapi/apis/overview.py
mcsmapi/apis/user.py
mcsmapi/models/__init__.py
mcsmapi/models/common.py
mcsmapi/models/daemon.py
mcsmapi/models/file.py
mcsmapi/models/image.py
mcsmapi/models/instance.py
mcsmapi/models/overview.py
mcsmapi/models/user.py
mcsmapi-0.1.7.dist-info/licenses/LICENSE
mcsmapi-0.1.7.dist-info/METADATA
mcsmapi-0.1.7.dist-info/WHEEL
mcsmapi-0.1.7.dist-info/top_level.txt
mcsmapi-0.1.7.dist-info/RECORD
