Metadata-Version: 2.4
Name: mcsmapi
Version: 0.1.7
Summary: Shortcut the pypi package of MCSM./快捷操作MCSM的pypi包
Author-email: molanp <molanpp@outlook.com>
License-Expression: MIT
Project-URL: Source, https://github.com/molanp/mcsmapi
Classifier: Programming Language :: Python :: 3
Classifier: Programming Language :: Python :: 3.10
Requires-Python: >=3.10
License-File: LICENSE
Requires-Dist: requests
Requires-Dist: pydantic>=2.0.0
Dynamic: license-file
